malexport/__init__.py
malexport/__main__.py
malexport/common.py
malexport/list_type.py
malexport/log.py
malexport/manual_episode.py
malexport/paths.py
malexport/py.typed
malexport/exporter/__init__.py
malexport/exporter/account.py
malexport/exporter/api_list.py
malexport/exporter/driver.py
malexport/exporter/export_downloader.py
malexport/exporter/forum.py
malexport/exporter/friends.py
malexport/exporter/history.py
malexport/exporter/mal_list.py
malexport/exporter/mal_session.py
malexport/exporter/messages.py
malexport/parse/__init__.py
malexport/parse/api_list.py
malexport/parse/combine.py
malexport/parse/common.py
malexport/parse/forum.py
malexport/parse/friends.py
malexport/parse/history.py
malexport/parse/mal_list.py
malexport/parse/messages.py
malexport/parse/recover_deleted_entries.py
malexport/parse/xml.py
malexport/utils/__init__.py
malexport/utils/compare_lists.py
malexport-0.1.6.dist-info/licenses/LICENSE
malexport-0.1.6.dist-info/METADATA
malexport-0.1.6.dist-info/WHEEL
malexport-0.1.6.dist-info/entry_points.txt
malexport-0.1.6.dist-info/top_level.txt
malexport-0.1.6.dist-info/RECORD
