Metadata-Version: 2.4
Name: malexport
Version: 0.1.6
Summary: backs up info from your MAL account
Author: purarue
License-Expression: MIT
Project-URL: Homepage, https://github.com/purarue/malexport
Keywords: anime,data,webscraping
Classifier: Programming Language :: Python
Classifier: Programming Language :: Python :: 3
Classifier: Programming Language :: Python :: 3 :: Only
Classifier: Programming Language :: Python :: 3.10
Classifier: Programming Language :: Python :: 3.11
Classifier: Programming Language :: Python :: 3.12
Classifier: Programming Language :: Python :: 3.13
Classifier: Programming Language :: Python :: 3.14
Requires-Python: >=3.10
License-File: LICENSE
Requires-Dist: PyYaml
Requires-Dist: backoff>=2.0.0
Requires-Dist: click>=8.0
Requires-Dist: cssselect
Requires-Dist: dateparser
Requires-Dist: gitpython
Requires-Dist: logzero
Requires-Dist: lxml
Requires-Dist: more-itertools
Requires-Dist: requests
Requires-Dist: selenium>=4.10.0
Requires-Dist: simplejson
Provides-Extra: manual
Requires-Dist: autotui; extra == "manual"
Requires-Dist: pyfzf-iter; extra == "manual"
Provides-Extra: recover
Requires-Dist: hpi; extra == "recover"
Provides-Extra: testing
Requires-Dist: flake8; extra == "testing"
Requires-Dist: mypy; extra == "testing"
Dynamic: license-file
